text/__init__.py
text/cleaners.py
text/cmudict.py
text/numbers.py
text/symbols.py
EmotiVoice-0.2.0.dist-info/LICENSE
EmotiVoice-0.2.0.dist-info/METADATA
EmotiVoice-0.2.0.dist-info/WHEEL
EmotiVoice-0.2.0.dist-info/top_level.txt
EmotiVoice-0.2.0.dist-info/RECORD
